<annotation>
	<folder>ImageSets</folder>
	<filename>69.jpg</filename>
	<path>C:\Users\s1026670\Documents\Python Scripts\Project Ideas\5. Segmentation\mmdetection_object_detection_demo\data\VOC2007\ImageSets\69.jpg</path>
	<source>
		<database>Unknown</database>
	</source>
	<size>
		<width>1600</width>
		<height>1200</height>
		<depth>3</depth>
	</size>
	<segmented>0</segmented>
	<object>
		<name>ear</name>
		<pose>Unspecified</pose>
		<truncated>0</truncated>
		<difficult>0</difficult>
		<bndbox>
			<xmin>119</xmin>
			<ymin>839</ymin>
			<xmax>231</xmax>
			<ymax>1017</ymax>
		</bndbox>
	</object>
	<object>
		<name>ear</name>
		<pose>Unspecified</pose>
		<truncated>0</truncated>
		<difficult>0</difficult>
		<bndbox>
			<xmin>587</xmin>
			<ymin>530</ymin>
			<xmax>782</xmax>
			<ymax>689</ymax>
		</bndbox>
	</object>
	<object>
		<name>ear</name>
		<pose>Unspecified</pose>
		<truncated>0</truncated>
		<difficult>0</difficult>
		<bndbox>
			<xmin>951</xmin>
			<ymin>346</ymin>
			<xmax>1003</xmax>
			<ymax>431</ymax>
		</bndbox>
	</object>
	<object>
		<name>ear</name>
		<pose>Unspecified</pose>
		<truncated>0</truncated>
		<difficult>0</difficult>
		<bndbox>
			<xmin>1408</xmin>
			<ymin>961</ymin>
			<xmax>1598</xmax>
			<ymax>1144</ymax>
		</bndbox>
	</object>
	<object>
		<name>ear</name>
		<pose>Unspecified</pose>
		<truncated>0</truncated>
		<difficult>0</difficult>
		<bndbox>
			<xmin>1452</xmin>
			<ymin>556</ymin>
			<xmax>1487</xmax>
			<ymax>603</ymax>
		</bndbox>
	</object>
	<object>
		<name>ear</name>
		<pose>Unspecified</pose>
		<truncated>0</truncated>
		<difficult>0</difficult>
		<bndbox>
			<xmin>3</xmin>
			<ymin>726</ymin>
			<xmax>47</xmax>
			<ymax>781</ymax>
		</bndbox>
	</object>
	<object>
		<name>ear</name>
		<pose>Unspecified</pose>
		<truncated>0</truncated>
		<difficult>0</difficult>
		<bndbox>
			<xmin>411</xmin>
			<ymin>523</ymin>
			<xmax>469</xmax>
			<ymax>721</ymax>
		</bndbox>
	</object>
</annotation>
